korre/__init__.py
korre/entity_label.json
korre/korre.py
korre/relid2label.json
korre/utils.py
gliner_korre-0.1.0.dist-info/METADATA
gliner_korre-0.1.0.dist-info/WHEEL
gliner_korre-0.1.0.dist-info/top_level.txt
gliner_korre-0.1.0.dist-info/RECORD
