Metadata-Version: 2.4
Name: gliner-korre
Version: 0.1.0
Summary: A Korean Relation Extraction library based on GLiNER
Author-email: lots-o <kgh0916@gmail.com>
Project-URL: Homepage, https://github.com/lots-o/korre
Project-URL: Upstream, https://github.com/datawhales/korre
Project-URL: Bug Tracker, https://github.com/lots-o/korre/issues
Classifier: Programming Language :: Python :: 3
Classifier: License :: OSI Approved :: MIT License
Classifier: Operating System :: OS Independent
Requires-Python: >=3.12
Requires-Dist: easydict>=1.13
Requires-Dist: gliner==0.2.16
Requires-Dist: python-mecab-ko>=1.3.7
Requires-Dist: wget>=3.2
